insynth/__init__.py
insynth/calculators/__init__.py
insynth/calculators/abstract_calculator.py
insynth/calculators/layer.py
insynth/calculators/neuron.py
insynth/data/__init__.py
insynth/data/utils.py
insynth/perturbators/__init__.py
insynth/perturbators/abstract_perturbator.py
insynth/perturbators/audio.py
insynth/perturbators/generic.py
insynth/perturbators/image.py
insynth/perturbators/pipeline.py
insynth/perturbators/text.py
insynth/runners/__init__.py
insynth/runners/extensive.py
insynth/runners/runner.py
insynth-1.0.2.dist-info/LICENSE
insynth-1.0.2.dist-info/METADATA
insynth-1.0.2.dist-info/WHEEL
insynth-1.0.2.dist-info/top_level.txt
insynth-1.0.2.dist-info/RECORD
