Metadata-Version: 2.1
Name: insynth
Version: 1.0.2
Summary: Domain-specific generation of test inputs for robustness testing of ML models
Home-page: https://github.com/mlxyz/insynth
Author: Marian Lambert
Author-email: marlambe@mail.uni-mannheim.de
License: UNKNOWN
Project-URL: Bug Tracker, https://github.com/mlxyz/insynth/issues
Platform: UNKNOWN
Classifier: Programming Language :: Python :: 3
Classifier: License :: OSI Approved :: MIT License
Classifier: Operating System :: OS Independent
Requires-Python: >=3.6
License-File: LICENSE
Requires-Dist: audiomentations
Requires-Dist: coverage
Requires-Dist: librosa
Requires-Dist: numpy
Requires-Dist: requests
Requires-Dist: scipy
Requires-Dist: tensorflow
Requires-Dist: tqdm
Requires-Dist: Pillow
Requires-Dist: pandas
Requires-Dist: pydub
Requires-Dist: scikit-learn
Requires-Dist: tensorflow-datasets
